{
  "indexes": [
    {
      "collectionGroup": "incidentZones",
      "queryScope": "COLLECTION",
      "fields": [
        {
          "fieldPath": "status",
          "order": "ASCENDING"
        },
        {
          "fieldPath": "riskRank",
          "order": "DESCENDING"
        },
        {
          "fieldPath": "updatedAt",
          "order": "DESCENDING"
        }
      ]
    }
  ],
  "fieldOverrides": [
    {
      "collectionGroup": "incidentZones",
      "fieldPath": "reportIds",
      "indexes": []
    }
  ]
}
